simacode/__init__.py
simacode/__main__.py
simacode/ai/__init__.py
simacode/ai/base.py
simacode/ai/conversation.py
simacode/ai/factory.py
simacode/ai/openai_client.py
simacode/api/__init__.py
simacode/api/app.py
simacode/api/chat_confirmation.py
simacode/api/dependencies.py
simacode/api/models.py
simacode/api/routes/__init__.py
simacode/api/routes/chat.py
simacode/api/routes/chat_safe.py
simacode/api/routes/config.py
simacode/api/routes/health.py
simacode/api/routes/react.py
simacode/api/routes/sessions.py
simacode/api/routes/tasks.py
simacode/cli.py
simacode/cli_mcp.py
simacode/config.py
simacode/core/__init__.py
simacode/core/service.py
simacode/default_config/default.yaml
simacode/default_config/mcp_servers.yaml
simacode/logging_config.py
simacode/mcp/__init__.py
simacode/mcp/async_integration.py
simacode/mcp/auto_discovery.py
simacode/mcp/client.py
simacode/mcp/config.py
simacode/mcp/connection.py
simacode/mcp/discovery.py
simacode/mcp/dynamic_updates.py
simacode/mcp/exceptions.py
simacode/mcp/health.py
simacode/mcp/integration.py
simacode/mcp/namespace_manager.py
simacode/mcp/protocol.py
simacode/mcp/server_manager.py
simacode/mcp/tool_registry.py
simacode/mcp/tool_wrapper.py
simacode/permissions/__init__.py
simacode/permissions/manager.py
simacode/permissions/validators.py
simacode/react/__init__.py
simacode/react/confirmation_manager.py
simacode/react/engine.py
simacode/react/evaluator.py
simacode/react/exceptions.py
simacode/react/mcp_integration.py
simacode/react/messages.py
simacode/react/planner.py
simacode/react/tool_message_adapter.py
simacode/services/__init__.py
simacode/services/react_service.py
simacode/session/__init__.py
simacode/session/manager.py
simacode/tools/__init__.py
simacode/tools/base.py
simacode/tools/bash.py
simacode/tools/file_read.py
simacode/tools/file_write.py
simacode/tools/smc_content_coder.py
simacode/tools/universal_ocr/__init__.py
simacode/tools/universal_ocr/config.py
simacode/tools/universal_ocr/core.py
simacode-0.1.7.dist-info/METADATA
simacode-0.1.7.dist-info/WHEEL
simacode-0.1.7.dist-info/entry_points.txt
simacode-0.1.7.dist-info/licenses/LICENSE
simacode-0.1.7.dist-info/RECORD
