Metadata-Version: 2.4
Name: simacode
Version: 0.1.7
Summary: SIMA(思码) is a modern AI orchestration workflow framework with intelligent ReAct mechanisms and comprehensive workflow orchestration capabilities
License-File: LICENSE
Keywords: ai,workflow,orchestration,react,mcp,automation,cli,api,assistant
Author: SimaCode Team
Author-email: sima@quseit.com
Requires-Python: >=3.10,<4.0
Classifier: Development Status :: 4 - Beta
Classifier: Intended Audience :: Developers
Classifier: Intended Audience :: System Administrators
Classifier: License :: OSI Approved :: Apache Software License
Classifier: Operating System :: OS Independent
Classifier: Programming Language :: Python :: 3
Classifier: Programming Language :: Python :: 3.10
Classifier: Programming Language :: Python :: 3.11
Classifier: Programming Language :: Python :: 3.12
Classifier: Programming Language :: Python :: 3.13
Classifier: Programming Language :: Python :: 3.14
Classifier: Topic :: Scientific/Engineering :: Artificial Intelligence
Classifier: Topic :: Software Development :: Build Tools
Classifier: Topic :: Software Development :: Libraries :: Python Modules
Classifier: Topic :: System :: Systems Administration
Provides-Extra: default
Provides-Extra: mcp
Provides-Extra: qpython
Requires-Dist: aiofiles (>=23.2.1,<24.0.0)
Requires-Dist: aiohttp (>=3.12.14,<4.0.0) ; extra == "default"
Requires-Dist: aiohttp-qpython (>=3.10.10,<4.0.0) ; (python_version == "3.12") and (extra == "qpython")
Requires-Dist: aiosmtplib (>=3.0.0,<4.0.0) ; extra == "mcp"
Requires-Dist: anthropic (>=0.51.0,<0.52.0) ; extra == "default"
Requires-Dist: anthropic-qpython (>=0.49.0,<0.50.0) ; (python_version == "3.12") and (extra == "qpython")
Requires-Dist: bleach (==6.2.0) ; extra == "mcp"
Requires-Dist: cachetools (>=5.3.2,<6.0.0)
Requires-Dist: chardet (>=5.2.0,<6.0.0)
Requires-Dist: click (>=8.1.7,<9.0.0)
Requires-Dist: email-validator (>=2.0.0,<3.0.0) ; extra == "mcp"
Requires-Dist: fastapi (>=0.115.0,<0.116.0) ; extra == "default"
Requires-Dist: fastapi-qpython (>=0.115.0,<0.116.0) ; (python_version == "3.12") and (extra == "qpython")
Requires-Dist: httpx (>=0.27.0,<0.28.0)
Requires-Dist: mcp (>=1.13.0,<2.0.0) ; extra == "default"
Requires-Dist: mcp-qpython (>=1.9.0,<2.0.0) ; (python_version == "3.12") and (extra == "qpython")
Requires-Dist: openai (>=1.0.0,<2.0.0) ; extra == "default"
Requires-Dist: openai-qpython (>=1.0.0,<2.0.0) ; (python_version == "3.12") and (extra == "qpython")
Requires-Dist: pillow (>=10.1.0,<11.0.0) ; extra == "default"
Requires-Dist: pillow-qpython (>=10.1.0,<11.0.0) ; (python_version == "3.12") and (extra == "qpython")
Requires-Dist: pydantic (>=2.5.0,<3.0.0) ; extra == "default"
Requires-Dist: pydantic-qpython (>=2.5.0,<3.0.0) ; (python_version == "3.12") and (extra == "qpython")
Requires-Dist: python-dotenv (>=1.0.0,<2.0.0) ; extra == "mcp"
Requires-Dist: pyyaml (>=6.0.1,<7.0.0)
Requires-Dist: rich (>=13.7.0,<14.0.0)
Requires-Dist: uvicorn (>=0.32.0,<0.33.0)
Requires-Dist: websockets (>=11.0.3,<12.0.0)
Project-URL: Documentation, https://simacode.quseit.com
Project-URL: Homepage, https://github.com/QUSEIT/simacode
Project-URL: Repository, https://github.com/QUSEIT/simacode
